elblog2dict/__init__.py
elblog2dict/parser.py
elblog2dict-1.0.1.dist-info/LICENSE
elblog2dict-1.0.1.dist-info/METADATA
elblog2dict-1.0.1.dist-info/WHEEL
elblog2dict-1.0.1.dist-info/top_level.txt
elblog2dict-1.0.1.dist-info/RECORD
