Metadata-Version: 2.1
Name: elblog2dict
Version: 1.0.1
Summary: Utility for parsing and extracting data from ELB logs
Home-page: https://github.com/leemhoon00/elblog2dict
Author: leemhoon00
Author-email: leemhoon000@gmail.com
License: MIT
Keywords: elb,log,parser,elblog2dict,regular expression
Classifier: Programming Language :: Python :: 3.6
Classifier: Programming Language :: Python :: 3.7
Classifier: Programming Language :: Python :: 3.8
Classifier: Programming Language :: Python :: 3.9
Requires-Python: >=3.6
License-File: LICENSE
